[
    {
        "keys": [
            "你好",
            "欢迎光临"
        ],
        "reply": "你好啊",
        "flag": true
    },
    {
        "keys": [
            "你好",
            "欢迎光临"
        ],
        "reply": "你好啊",
        "flag": true
    },
    {
        "keys": [
            "你好",
            "欢迎光临"
        ],
        "reply": "你好啊",
        "flag": true
    },
    {
        "keys": [
            "你好",
            "欢迎光临"
        ],
        "reply": "你好啊",
        "flag": true
    },
    {
        "keys": [
            "你好",
            "欢迎光临"
        ],
        "reply": "你好啊",
        "flag": false
    },
    {
        "keys": [
            "你好",
            "欢迎光临"
        ],
        "reply": "你好啊",
        "flag": false
    },
    {
        "keys": [
            "你好",
            "欢迎光临"
        ],
        "reply": "你好啊",
        "flag": true
    }
]
